tests/__init__.py
tests/conftest.py
tests/test_diffenv.py
tests/test_env_hvac.py
tests/test_env_linear_navigation_2d.py
tests/test_env_lqr_navigation.py
tests/test_env_navigation.py
tests/test_env_navigation_lqr.py
tests/test_env_reservoir.py
tests/test_hvac.py
tests/test_ilqr.py
tests/test_linear_navigation_2d.py
tests/test_lqr.py
tests/test_lqr_problems.py
tests/test_lqr_solvers.py
tests/test_reservoir.py
tests/test_trajectory.py
tests/test_utils_optimization.py
tfmpc/__init__.py
tfmpc/agents/__init__.py
tfmpc/agents/mpc.py
tfmpc/envs/__init__.py
tfmpc/envs/diffenv.py
tfmpc/envs/gymenv.py
tfmpc/envs/navigation.py
tfmpc/envs/hvac/__init__.py
tfmpc/envs/lqr/__init__.py
tfmpc/envs/lqr/navigation/__init__.py
tfmpc/envs/navigation/__init__.py
tfmpc/envs/navigation_lqr/__init__.py
tfmpc/envs/reservoir/__init__.py
tfmpc/launchers/__init__.py
tfmpc/loggers/__init__.py
tfmpc/loggers/py_logging.py
tfmpc/loggers/wandb.py
tfmpc/problems/__init__.py
tfmpc/problems/lqr.py
tfmpc/runners/__init__.py
tfmpc/solvers/__init__.py
tfmpc/solvers/ilqr.py
tfmpc/solvers/lqr.py
tfmpc-0.8.0.dist-info/LICENSE
tfmpc-0.8.0.dist-info/METADATA
tfmpc-0.8.0.dist-info/WHEEL
tfmpc-0.8.0.dist-info/entry_points.txt
tfmpc-0.8.0.dist-info/top_level.txt
tfmpc-0.8.0.dist-info/RECORD
