Metadata-Version: 2.1
Name: tfmpc
Version: 0.8.0
Summary: An implementation of model-predictive control algorithms using TensorFlow 2
Home-page: https://github.com/thiagopbueno/tf-mpc
Author: Thiago P. Bueno
Author-email: thiago.pbueno@gmail.com
License: GNU General Public License v3.0
Keywords: model-predictive-control,mpc,tensorflow2
Platform: UNKNOWN
Classifier: Development Status :: 3 - Alpha
Classifier: Environment :: Console
Classifier: Intended Audience :: Science/Research
Classifier: License :: OSI Approved :: GNU General Public License v3 (GPLv3)
Classifier: Natural Language :: English
Classifier: Operating System :: OS Independent
Classifier: Programming Language :: Python :: 3
Classifier: Topic :: Scientific/Engineering :: Artificial Intelligence
Requires-Python: >=3.6
Requires-Dist: Click
Requires-Dist: fire
Requires-Dist: gym
Requires-Dist: tensorflow-cpu
Requires-Dist: tensorflow-probability
Requires-Dist: sklearn
Requires-Dist: pandas
Requires-Dist: psutil
Requires-Dist: pytest
Requires-Dist: tuneconfig
